bi_toolbox/Reporting/Processors.py
bi_toolbox/Reporting/__init__.py
bi_toolbox/__init__.py
bi_toolbox/utils/CredManager.py
bi_toolbox/utils/__init__.py
bi_toolbox-0.1.0a1.dist-info/LICENSE
bi_toolbox-0.1.0a1.dist-info/METADATA
bi_toolbox-0.1.0a1.dist-info/WHEEL
bi_toolbox-0.1.0a1.dist-info/RECORD
