Metadata-Version: 2.1
Name: bi_toolbox
Version: 0.1.0a1
Summary: An efficient and simple to use wrapper for streamlining BI workflows, integrating seamlessly with cloud services, databases, and reporting tools.
Home-page: https://bi-toolbox.amrsherif.live/
License: Apache-2.0
Keywords: BI,reporting,S3,Slack,Google Sheets,database,Redshift,Postgres
Author: Amr Sherif
Author-email: amr.achraff@gmail.com
Maintainer: Amr Sherif
Maintainer-email: amr.achraff@gmail.com
Requires-Python: >=3.9,<4.0
Classifier: Development Status :: 3 - Alpha
Classifier: Intended Audience :: Developers
Classifier: Intended Audience :: Information Technology
Classifier: Intended Audience :: Science/Research
Classifier: License :: OSI Approved :: Apache Software License
Classifier: Programming Language :: Python :: 3
Classifier: Programming Language :: Python :: 3.9
Classifier: Programming Language :: Python :: 3.10
Classifier: Programming Language :: Python :: 3.11
Classifier: Programming Language :: Python :: 3.12
Classifier: Topic :: Scientific/Engineering :: Artificial Intelligence
Classifier: Topic :: Scientific/Engineering :: Information Analysis
Classifier: Topic :: Scientific/Engineering :: Visualization
Classifier: Topic :: Software Development :: Libraries
Requires-Dist: SQLAlchemy (>=2.0.0,<3.0.0)
Requires-Dist: boto3 (>=1.17.0,<2.0.0)
Requires-Dist: dask (>=2024.8.0,<2025.0.0)
Requires-Dist: google-auth (>=2.34.0,<3.0.0)
Requires-Dist: google-auth-oauthlib (>=1.2.1,<2.0.0)
Requires-Dist: gspread (>=6.1.2,<7.0.0)
Requires-Dist: gspread-dataframe (>=4.0.0,<5.0.0)
Requires-Dist: pandas (>=2.2.0,<3.0.0)
Requires-Dist: pydantic (>=2.9.0,<3.0.0)
Requires-Dist: pydrive (>=1.3.1,<2.0.0)
Requires-Dist: python-dotenv (>=1.0.0,<2.0.0)
Requires-Dist: slack-sdk (>=3.32.0,<4.0.0)
Project-URL: Documentation, https://bi-toolbox.amrsherif.live/en/latest/reference.html
Project-URL: Repository, https://github.com/amr-sheriff/BI-Toolbox/tree/main
